sencha
