Metadata-Version: 1.1
Name: django-sencha
Version: 1.2.5
Summary: Django project contain static files about extjs 4.2
Home-page: http://cellarosi@bitbucket.org/cellarosi/django-sencha
Author: Marco Cellarosi
Author-email: cellarosi@gmail.com
License: MIT
Keywords: django,sencha,extjs,staticfiles
Platform: any
Classifier: Development Status :: 5 - Production/Stable
Classifier: Environment :: Web Environment
Classifier: Framework :: Django
Classifier: Intended Audience :: Developers
Classifier: Natural Language :: English
Classifier: License :: OSI Approved :: MIT License
Classifier: Operating System :: OS Independent
Classifier: Programming Language :: Python
Classifier: Topic :: Utilities
